buffered_async_iterators/__init__.py
buffered_async_iterators/_buffered.py
buffered_async_iterators/_buffered_3_7.py
buffered_async_iterators/_buffered_3_8.py
buffered_async_iterators-1.0.2.dist-info/LICENSE
buffered_async_iterators-1.0.2.dist-info/METADATA
buffered_async_iterators-1.0.2.dist-info/WHEEL
buffered_async_iterators-1.0.2.dist-info/top_level.txt
buffered_async_iterators-1.0.2.dist-info/RECORD
