Metadata-Version: 2.1
Name: buffered-async-iterators
Version: 1.0.2
Summary: A simple implementation of buffered async iterators, allowing more throughput by letting iterators run while their loop bodied are being executed.
License: mit
Project-URL: Bug Tracker, https://github.com/SimpleArt/buffered-async-iterators/issues
Project-URL: Repository, https://github.com/SimpleArt/buffered-async-iterators
Keywords: asyncio,buffered,iterator
Classifier: Framework :: AsyncIO
Classifier: Development Status :: 6 - Mature
Classifier: License :: OSI Approved :: MIT License
Classifier: Programming Language :: Python :: 3.7
Classifier: Programming Language :: Python :: 3.8
Classifier: Programming Language :: Python :: 3.9
Classifier: Programming Language :: Python :: 3.10
Classifier: Programming Language :: Python :: 3.11
Classifier: Programming Language :: Python :: 3.12
Classifier: Operating System :: OS Independent
Classifier: Intended Audience :: Developers
Classifier: Typing :: Typed
Requires-Python: >=3.7
License-File: LICENSE
